memoria/__init__.py
memoria/ai_enhancer.py
memoria/core.py
memoria/exporter.py
memoria/ingestor.py
memoria/privacy.py
memoria/utils.py
memoria_tool-1.0.0.dist-info/licenses/LICENCE
memoria_tool-1.0.0.dist-info/METADATA
memoria_tool-1.0.0.dist-info/WHEEL
memoria_tool-1.0.0.dist-info/top_level.txt
memoria_tool-1.0.0.dist-info/RECORD
