Metadata-Version: 2.4
Name: memoria-tool
Version: 1.0.0
Summary: Local-first digital memory management library with semantic AI and privacy controls.
Home-page: https://github.com/imGJUser1/memoria-tool
Author: IM_GJ
Author-email: IM_GJ <imgj.3195@gmail.com>
Project-URL: Repository, https://github.com/imGJUser1/memoria-tool
Project-URL: Documentation, https://pypi.org/project/memoria-tool/
Keywords: memory,ai,privacy,semantic-search,faiss,transformers
Requires-Python: >=3.9
License-File: LICENCE
Requires-Dist: faiss-cpu
Requires-Dist: sentence-transformers
Requires-Dist: cryptography
Requires-Dist: sqlalchemy
Requires-Dist: watchdog
Requires-Dist: pandas
Requires-Dist: numpy
Requires-Dist: browserhistory
Requires-Dist: transformers
Requires-Dist: scikit-learn
Requires-Dist: nltk
Provides-Extra: cloud
Requires-Dist: google-generativeai; extra == "cloud"
Requires-Dist: openai; extra == "cloud"
Requires-Dist: anthropic; extra == "cloud"
Requires-Dist: slack-sdk; extra == "cloud"
Requires-Dist: google-api-python-client; extra == "cloud"
Requires-Dist: google-auth-oauthlib; extra == "cloud"
Requires-Dist: google-auth; extra == "cloud"
Requires-Dist: notion-client; extra == "cloud"
Requires-Dist: whatsapp-python; extra == "cloud"
Dynamic: author
Dynamic: home-page
Dynamic: license-file
Dynamic: requires-python
